metalibraries/__init__.py
metalibraries/metalibraries.py
metalibraries-0.2.3.dist-info/LICENSE
metalibraries-0.2.3.dist-info/METADATA
metalibraries-0.2.3.dist-info/WHEEL
metalibraries-0.2.3.dist-info/top_level.txt
metalibraries-0.2.3.dist-info/RECORD
