Metadata-Version: 2.1
Name: metalibraries
Version: 0.2.3
Summary: Metalibraries is a Python package that provides modular, reusable libraries designed to streamline development and improve code organization across various projects.
Home-page: https://github.com/anaferreira150965/metalibraries
Author: Ana Ferreira
Project-URL: Homepage, https://github.com/anaferreira150965/metalibraries
Project-URL: Issues, https://github.com/anaferreira150965/metalibraries/issues
Classifier: Programming Language :: Python :: 3
Classifier: License :: OSI Approved :: The Unlicense (Unlicense)
Classifier: Operating System :: OS Independent
Requires-Python: >=3.10
License-File: LICENSE
